redlibssh-2.0.9.dist-info/METADATA
redlibssh-2.0.9.dist-info/RECORD
redlibssh-2.0.9.dist-info/LICENSE
redlibssh-2.0.9.dist-info/top_level.txt
redlibssh-2.0.9.dist-info/WHEEL
redlibssh-2.0.9.dist-info/COPYING
redlibssh.libs/libpcre-9513aab5.so.1.2.0
redlibssh.libs/libk5crypto-b1f99d5c.so.3.1
redlibssh.libs/libcrypto-19957f5b.so.1.0.2k
redlibssh.libs/libselinux-0922c95c.so.1
redlibssh.libs/libkrb5-fcafa220.so.3.3
redlibssh.libs/libgssapi_krb5-497db0c6.so.2.2
redlibssh.libs/libcom_err-2abe824b.so.2.1
redlibssh.libs/libkeyutils-dfe70bd6.so.1.5
redlibssh.libs/libkrb5support-d0bcff84.so.0.1
redlibssh.libs/libssh-3c042a37.so.4.8.7
ssh/sftp_handles.cpython-36m-x86_64-linux-gnu.so
ssh/callbacks.cpython-36m-x86_64-linux-gnu.so
ssh/exceptions.cpython-36m-x86_64-linux-gnu.so
ssh/__init__.py
ssh/utils.pyx
ssh/sftp_statvfs.cpython-36m-x86_64-linux-gnu.so
ssh/sftp_handles.pyx
ssh/connector.c
ssh/scp.c
ssh/sftp.pxd
ssh/tunnel.pxd
ssh/utils.c
ssh/sftp_attributes.cpython-36m-x86_64-linux-gnu.so
ssh/callbacks.pxd
ssh/utils.cpython-36m-x86_64-linux-gnu.so
ssh/connector.pyx
ssh/error_codes.cpython-36m-x86_64-linux-gnu.so
ssh/key.c
ssh/options.c
ssh/keytypes.pyx
ssh/libssh_enums.pyx
ssh/scp.cpython-36m-x86_64-linux-gnu.so
ssh/event.cpython-36m-x86_64-linux-gnu.so
ssh/sftp_statvfs.pyx
ssh/tunnel.c
ssh/c_legacy.pxd
ssh/callbacks.c
ssh/c_ssh.pxd
ssh/session.pyx
ssh/tunnel.cpython-36m-x86_64-linux-gnu.so
ssh/c_callbacks.pxd
ssh/session.cpython-36m-x86_64-linux-gnu.so
ssh/keytypes.cpython-36m-x86_64-linux-gnu.so
ssh/exceptions.pyx
ssh/callbacks.pyx
ssh/channel.pxd
ssh/sftp.pyx
ssh/sftp_attributes.pxd
ssh/c_ssh2.pxd
ssh/sftp_handles.c
ssh/_version.py
ssh/sftp_statvfs.pxd
ssh/connector.pxd
ssh/event.pyx
ssh/connector.cpython-36m-x86_64-linux-gnu.so
ssh/channel.c
ssh/event.c
ssh/options.pyx
ssh/sftp_attributes.pyx
ssh/tunnel.pyx
ssh/exceptions.c
ssh/libssh_enums.c
ssh/channel.cpython-36m-x86_64-linux-gnu.so
ssh/keytypes.pxd
ssh/options.pxd
ssh/sftp.cpython-36m-x86_64-linux-gnu.so
ssh/utils.pxd
ssh/key.cpython-36m-x86_64-linux-gnu.so
ssh/sftp_statvfs.c
ssh/channel.pyx
ssh/sftp_attributes.c
ssh/key.pxd
ssh/event.pxd
