Metadata-Version: 2.1
Name: redlibssh
Version: 2.0.9
Summary: Alternate bindings for libssh C library
Home-page: https://github.com/Red-M/Redlibssh
Author: Red_M
Author-email: redlibssh_pypi@red-m.net
License: LGPLv2.1
Platform: any
Classifier: Development Status :: 4 - Beta
Classifier: License :: OSI Approved :: GNU Lesser General Public License v2 (LGPLv2)
Classifier: Intended Audience :: Developers
Classifier: Operating System :: OS Independent
Classifier: Programming Language :: C
Classifier: Programming Language :: Python
Classifier: Programming Language :: Python :: 3
Classifier: Programming Language :: Python :: 3.6
Classifier: Programming Language :: Python :: 3.7
Classifier: Programming Language :: Python :: 3.8
Classifier: Programming Language :: Python :: 3.9
Classifier: Programming Language :: Python :: 3.10
Classifier: Topic :: System :: Shells
Classifier: Topic :: System :: Networking
Classifier: Topic :: Software Development :: Libraries
Classifier: Topic :: Software Development :: Libraries :: Python Modules
Classifier: Operating System :: POSIX
Classifier: Operating System :: POSIX :: Linux
Classifier: Operating System :: POSIX :: BSD
Classifier: Operating System :: MacOS :: MacOS X
License-File: LICENSE
License-File: COPYING
Provides-Extra: tests
Requires-Dist: safety ; extra == 'tests'
Requires-Dist: pytest-cov ; extra == 'tests'
Requires-Dist: bandit ; extra == 'tests'
Requires-Dist: coveralls ; extra == 'tests'
Requires-Dist: pylint ; extra == 'tests'
